{"id":"3XHaaZqNPSJAFq6B7EP2X","title":"Lecture 6","vault":{"fsPath":"vault"},"type":"note","desc":"","links":[],"anchors":{"external-hardware-interrupts":{"type":"header","text":"External Hardware Interrupts","value":"external-hardware-interrupts","line":8,"column":0},"activation":{"type":"header","text":"Activation","value":"activation","line":10,"column":0},"features":{"type":"header","text":"Features","value":"features","line":15,"column":0},"gifr":{"type":"header","text":"GIFR","value":"gifr","line":27,"column":0},"minimum-timing-of-interrupt-signal":{"type":"header","text":"Minimum timing of Interrupt Signal","value":"minimum-timing-of-interrupt-signal","line":33,"column":0},"examples":{"type":"header","text":"Examples","value":"examples","line":38,"column":0},"interrupt-priority":{"type":"header","text":"Interrupt Priority","value":"interrupt-priority","line":63,"column":0}},"fname":"courses.Semester 5.Embedded Systems.Lecture 6","updated":1632723791302,"created":1632723062497,"parent":"a1PatlsCiz7PYsL111lFm","children":[],"data":{},"contentHash":"8d3e4dc78d118467df87678d15094d10","custom":{}}
