{"id":"lheZKOdjHCWZJ4Qy2gPeI","title":"Extra Practice Questions","vault":{"fsPath":"vault"},"type":"note","desc":"","links":[],"anchors":{"folder-link-mid-sem-papers":{"type":"header","text":"Folder Link Mid sem Papers","value":"folder-link-mid-sem-papers","line":11,"column":0},"past-year-mid-sem-solutions":{"type":"header","text":"Past year mid sem solutions","value":"past-year-mid-sem-solutions","line":13,"column":0},"mid-sem-2020-q6":{"type":"header","text":"Mid sem 2020 Q6","value":"mid-sem-2020-q6","line":15,"column":0},"mid-sem-2020-q7":{"type":"header","text":"Mid sem 2020 Q7","value":"mid-sem-2020-q7","line":49,"column":0},"mid-sem-2019-q5":{"type":"header","text":"Mid sem 2019 Q5","value":"mid-sem-2019-q5","line":107,"column":0},"mid-sem-2019-q6":{"type":"header","text":"Mid sem 2019 Q6","value":"mid-sem-2019-q6","line":130,"column":0},"mid-sem-2019-q7":{"type":"header","text":"Mid sem 2019 Q7","value":"mid-sem-2019-q7","line":159,"column":0},"mid-sem-2018-q4":{"type":"header","text":"Mid sem 2018 Q4","value":"mid-sem-2018-q4","line":194,"column":0},"mid-sem-2018-q5":{"type":"header","text":"Mid sem 2018 Q5","value":"mid-sem-2018-q5","line":219,"column":0},"mid-sem-2018-q6":{"type":"header","text":"Mid sem 2018 Q6","value":"mid-sem-2018-q6","line":249,"column":0},"question-1":{"type":"header","text":"Question 1","value":"question-1","line":297,"column":0},"question-2":{"type":"header","text":"Question 2","value":"question-2","line":330,"column":0},"question-3":{"type":"header","text":"Question 3","value":"question-3","line":360,"column":0},"question-4":{"type":"header","text":"Question 4","value":"question-4","line":394,"column":0},"question-5":{"type":"header","text":"Question 5","value":"question-5","line":436,"column":0},"question-6":{"type":"header","text":"Question 6","value":"question-6","line":480,"column":0}},"fname":"courses.Semester 5.Embedded Systems.Extra Practice Questions","updated":1633248099143,"created":1633146584123,"parent":"a1PatlsCiz7PYsL111lFm","children":[],"data":{},"contentHash":"638d00f264a0291b5ab04fc9edcb89d8","custom":{}}
